simpleCalpackage/__init__.py
simpleCalpackage/add.py
simpleCalpackage/subtract.py
simpleCalpackage/extras/__init__.py
simpleCalpackage/extras/divide.py
simpleCalpackage/extras/multiply.py
simpleCalpackage-0.0.3.dist-info/METADATA
simpleCalpackage-0.0.3.dist-info/WHEEL
simpleCalpackage-0.0.3.dist-info/top_level.txt
simpleCalpackage-0.0.3.dist-info/RECORD
